nxscli/__init__.py
nxscli/__main__.py
nxscli/ext_commands.py
nxscli/ext_interfaces.py
nxscli/ext_plugins.py
nxscli/idata.py
nxscli/iplugin.py
nxscli/logger.py
nxscli/phandler.py
nxscli/plugins_loader.py
nxscli/pluginthr.py
nxscli/py.typed
nxscli/trigger.py
nxscli/cli/environment.py
nxscli/cli/main.py
nxscli/cli/types.py
nxscli/commands/cmd_csv.py
nxscli/commands/cmd_devinfo.py
nxscli/commands/cmd_none.py
nxscli/commands/cmd_printer.py
nxscli/commands/cmd_udp.py
nxscli/commands/config/cmd_chan.py
nxscli/commands/config/cmd_trig.py
nxscli/commands/interface/cmd_dummy.py
nxscli/commands/interface/cmd_rtt.py
nxscli/commands/interface/cmd_serial.py
nxscli/plugins/csv.py
nxscli/plugins/devinfo.py
nxscli/plugins/none.py
nxscli/plugins/printer.py
nxscli/plugins/udp.py
nxscli-0.5.1.dist-info/LICENSE
nxscli-0.5.1.dist-info/METADATA
nxscli-0.5.1.dist-info/WHEEL
nxscli-0.5.1.dist-info/entry_points.txt
nxscli-0.5.1.dist-info/top_level.txt
nxscli-0.5.1.dist-info/RECORD
